Metadata-Version: 2.1
Name: python-openhab-eventbus
Version: 1.0.0
Summary: An MQTT Event Bus for openHAB.
Home-page: https://github.com/Michdo93/python-openhab-eventbus
Download-URL: https://github.com/Michdo93/python-openhab-eventbus
Author: Michael Dörflinger
Author-email: michaeldoerflinger93@gmail.com
License: MIT License
Project-URL: Bug Tracker, https://github.com/Michdo93/python-openhab-eventbus/issues
Project-URL: Documentation, https://github.com/Michdo93/python-openhab-eventbus/blob/main/README.md
Project-URL: Source Code, https://github.com/Michdo93/python-openhab-eventbus
Keywords: openHAB
Classifier: Development Status :: 4 - Beta
Classifier: License :: OSI Approved :: MIT License
Classifier: Intended Audience :: Developers
Classifier: Operating System :: OS Independent
Classifier: Programming Language :: Python :: 3
Classifier: Programming Language :: Python :: 3 :: Only
Requires-Python: >=3.5
License-File: LICENSE
Requires-Dist: python-openhab-itemevents (>=0.1.2)
Requires-Dist: python-openhab-crud (>=0.1.2)
Requires-Dist: paho-mqtt (>=1.6.1)
